[
  {
    "ContainingType": "GestionProduit.API.Controllers.AuthController",
    "Method": "SignIn",
    "RelativePath": "api/Auth/signin",
    "HttpMethod": "POST",
    "IsController": true,
    "Order": 0,
    "Parameters": [
      {
        "Name": "dto",
        "Type": "GestionProduit.Application.DTOs.SignInRequestDto",
        "IsRequired": true
      }
    ],
    "ReturnTypes": []
  },
  {
    "ContainingType": "GestionProduit.API.Controllers.AuthController",
    "Method": "SignUp",
    "RelativePath": "api/Auth/signup",
    "HttpMethod": "POST",
    "IsController": true,
    "Order": 0,
    "Parameters": [
      {
        "Name": "dto",
        "Type": "GestionProduit.Application.DTOs.RegisterDto",
        "IsRequired": true
      }
    ],
    "ReturnTypes": []
  },
  {
    "ContainingType": "GestionProduit.API.Controllers.CommandesController",
    "Method": "Creer",
    "RelativePath": "api/Commandes",
    "HttpMethod": "POST",
    "IsController": true,
    "Order": 0,
    "Parameters": [
      {
        "Name": "input",
        "Type": "GestionProduit.Application.DTOs.CommandeCreateDto",
        "IsRequired": true
      }
    ],
    "ReturnTypes": [
      {
        "Type": "GestionProduit.Application.DTOs.CommandeDto",
        "MediaTypes": [
          "text/plain",
          "application/json",
          "text/json"
        ],
        "StatusCode": 200
      }
    ]
  },
  {
    "ContainingType": "GestionProduit.API.Controllers.CommandesController",
    "Method": "GetById",
    "RelativePath": "api/Commandes/{id}",
    "HttpMethod": "GET",
    "IsController": true,
    "Order": 0,
    "Parameters": [
      {
        "Name": "id",
        "Type": "System.Int32",
        "IsRequired": true
      }
    ],
    "ReturnTypes": [
      {
        "Type": "GestionProduit.Application.DTOs.CommandeDto",
        "MediaTypes": [
          "text/plain",
          "application/json",
          "text/json"
        ],
        "StatusCode": 200
      }
    ]
  },
  {
    "ContainingType": "GestionProduit.API.Controllers.CommandesController",
    "Method": "Annuler",
    "RelativePath": "api/Commandes/{id}/annuler",
    "HttpMethod": "POST",
    "IsController": true,
    "Order": 0,
    "Parameters": [
      {
        "Name": "id",
        "Type": "System.Int32",
        "IsRequired": true
      }
    ],
    "ReturnTypes": []
  },
  {
    "ContainingType": "GestionProduit.API.Controllers.CommandesController",
    "Method": "ChangerStatut",
    "RelativePath": "api/Commandes/{id}/statut",
    "HttpMethod": "PATCH",
    "IsController": true,
    "Order": 0,
    "Parameters": [
      {
        "Name": "id",
        "Type": "System.Int32",
        "IsRequired": true
      },
      {
        "Name": "value",
        "Type": "System.String",
        "IsRequired": false
      }
    ],
    "ReturnTypes": []
  },
  {
    "ContainingType": "GestionProduit.API.Controllers.CommandesController",
    "Method": "GetAllCommandes",
    "RelativePath": "api/Commandes/all",
    "HttpMethod": "GET",
    "IsController": true,
    "Order": 0,
    "Parameters": [
      {
        "Name": "statut",
        "Type": "System.String",
        "IsRequired": false
      }
    ],
    "ReturnTypes": [
      {
        "Type": "System.Collections.Generic.List\u00601[[GestionProduit.Application.DTOs.CommandeDto, GestionProduit.Application, Version=1.0.0.0, Culture=neutral, PublicKeyToken=null]]",
        "MediaTypes": [
          "text/plain",
          "application/json",
          "text/json"
        ],
        "StatusCode": 200
      }
    ]
  },
  {
    "ContainingType": "GestionProduit.API.Controllers.CommandesController",
    "Method": "MesCommandes",
    "RelativePath": "api/Commandes/mes",
    "HttpMethod": "GET",
    "IsController": true,
    "Order": 0,
    "Parameters": [],
    "ReturnTypes": [
      {
        "Type": "System.Collections.Generic.List\u00601[[GestionProduit.Application.DTOs.CommandeDto, GestionProduit.Application, Version=1.0.0.0, Culture=neutral, PublicKeyToken=null]]",
        "MediaTypes": [
          "text/plain",
          "application/json",
          "text/json"
        ],
        "StatusCode": 200
      }
    ]
  },
  {
    "ContainingType": "GestionProduit.API.Controllers.PanierController",
    "Method": "RetirerDuPanier",
    "RelativePath": "api/Panier/{panierItemId}",
    "HttpMethod": "DELETE",
    "IsController": true,
    "Order": 0,
    "Parameters": [
      {
        "Name": "panierItemId",
        "Type": "System.Int32",
        "IsRequired": true
      }
    ],
    "ReturnTypes": []
  },
  {
    "ContainingType": "GestionProduit.API.Controllers.PanierController",
    "Method": "AjouterAuPanier",
    "RelativePath": "api/Panier/ajouter",
    "HttpMethod": "POST",
    "IsController": true,
    "Order": 0,
    "Parameters": [
      {
        "Name": "produitId",
        "Type": "System.Int32",
        "IsRequired": false
      },
      {
        "Name": "quantite",
        "Type": "System.Int32",
        "IsRequired": false
      }
    ],
    "ReturnTypes": [
      {
        "Type": "GestionProduit.Application.DTOs.PanierDto",
        "MediaTypes": [
          "text/plain",
          "application/json",
          "text/json"
        ],
        "StatusCode": 200
      }
    ]
  },
  {
    "ContainingType": "GestionProduit.API.Controllers.PanierController",
    "Method": "GetPanier",
    "RelativePath": "api/Panier/liste",
    "HttpMethod": "GET",
    "IsController": true,
    "Order": 0,
    "Parameters": [],
    "ReturnTypes": [
      {
        "Type": "System.Collections.Generic.List\u00601[[GestionProduit.Application.DTOs.PanierDto, GestionProduit.Application, Version=1.0.0.0, Culture=neutral, PublicKeyToken=null]]",
        "MediaTypes": [
          "text/plain",
          "application/json",
          "text/json"
        ],
        "StatusCode": 200
      }
    ]
  },
  {
    "ContainingType": "GestionProduit.API.Controllers.PanierController",
    "Method": "ViderPanier",
    "RelativePath": "api/Panier/vider",
    "HttpMethod": "DELETE",
    "IsController": true,
    "Order": 0,
    "Parameters": [],
    "ReturnTypes": []
  },
  {
    "ContainingType": "GestionProduit.API.Controllers.ProduitController",
    "Method": "GetAll",
    "RelativePath": "api/Produit",
    "HttpMethod": "GET",
    "IsController": true,
    "Order": 0,
    "Parameters": [],
    "ReturnTypes": [
      {
        "Type": "System.Collections.Generic.List\u00601[[GestionProduit.Domain.Entities.Produit, GestionProduit.Domain, Version=1.0.0.0, Culture=neutral, PublicKeyToken=null]]",
        "MediaTypes": [
          "text/plain",
          "application/json",
          "text/json"
        ],
        "StatusCode": 200
      }
    ]
  },
  {
    "ContainingType": "GestionProduit.API.Controllers.ProduitController",
    "Method": "Create",
    "RelativePath": "api/Produit",
    "HttpMethod": "POST",
    "IsController": true,
    "Order": 0,
    "Parameters": [
      {
        "Name": "Id",
        "Type": "System.Int32",
        "IsRequired": false
      },
      {
        "Name": "Nom",
        "Type": "System.String",
        "IsRequired": false
      },
      {
        "Name": "Prix",
        "Type": "System.Decimal",
        "IsRequired": false
      },
      {
        "Name": "Stock",
        "Type": "System.Int32",
        "IsRequired": false
      },
      {
        "Name": "Description",
        "Type": "System.String",
        "IsRequired": false
      },
      {
        "Name": "ImageUrl",
        "Type": "System.String",
        "IsRequired": false
      }
    ],
    "ReturnTypes": []
  },
  {
    "ContainingType": "GestionProduit.API.Controllers.ProduitController",
    "Method": "GetById",
    "RelativePath": "api/Produit/{id}",
    "HttpMethod": "GET",
    "IsController": true,
    "Order": 0,
    "Parameters": [
      {
        "Name": "id",
        "Type": "System.Int32",
        "IsRequired": true
      }
    ],
    "ReturnTypes": [
      {
        "Type": "GestionProduit.Domain.Entities.Produit",
        "MediaTypes": [
          "text/plain",
          "application/json",
          "text/json"
        ],
        "StatusCode": 200
      }
    ]
  },
  {
    "ContainingType": "GestionProduit.API.Controllers.ProduitController",
    "Method": "Update",
    "RelativePath": "api/Produit/{id}",
    "HttpMethod": "PUT",
    "IsController": true,
    "Order": 0,
    "Parameters": [
      {
        "Name": "id",
        "Type": "System.Int32",
        "IsRequired": true
      },
      {
        "Name": "Id",
        "Type": "System.Int32",
        "IsRequired": false
      },
      {
        "Name": "Nom",
        "Type": "System.String",
        "IsRequired": false
      },
      {
        "Name": "Prix",
        "Type": "System.Decimal",
        "IsRequired": false
      },
      {
        "Name": "Stock",
        "Type": "System.Int32",
        "IsRequired": false
      },
      {
        "Name": "Description",
        "Type": "System.String",
        "IsRequired": false
      },
      {
        "Name": "ImageUrl",
        "Type": "System.String",
        "IsRequired": false
      }
    ],
    "ReturnTypes": []
  },
  {
    "ContainingType": "GestionProduit.API.Controllers.ProduitController",
    "Method": "Delete",
    "RelativePath": "api/Produit/{id}",
    "HttpMethod": "DELETE",
    "IsController": true,
    "Order": 0,
    "Parameters": [
      {
        "Name": "id",
        "Type": "System.Int32",
        "IsRequired": true
      }
    ],
    "ReturnTypes": []
  },
  {
    "ContainingType": "GestionProduit.API.Controllers.ProduitController",
    "Method": "UploadImage",
    "RelativePath": "api/Produit/upload-image/{id}",
    "HttpMethod": "POST",
    "IsController": true,
    "Order": 0,
    "Parameters": [
      {
        "Name": "id",
        "Type": "System.Int32",
        "IsRequired": true
      },
      {
        "Name": "file",
        "Type": "Microsoft.AspNetCore.Http.IFormFile",
        "IsRequired": false
      }
    ],
    "ReturnTypes": []
  },
  {
    "ContainingType": "GestionProduit.API.Controllers.TestEmailController",
    "Method": "SendTestEmail",
    "RelativePath": "api/test/send-email",
    "HttpMethod": "POST",
    "IsController": true,
    "Order": 0,
    "Parameters": [
      {
        "Name": "toEmail",
        "Type": "System.String",
        "IsRequired": false
      }
    ],
    "ReturnTypes": []
  },
  {
    "ContainingType": "GestionProduit.API.Controllers.UserController",
    "Method": "GetAllUsers",
    "RelativePath": "api/User",
    "HttpMethod": "GET",
    "IsController": true,
    "Order": 0,
    "Parameters": [],
    "ReturnTypes": [
      {
        "Type": "System.Collections.Generic.List\u00601[[GestionProduit.Domain.Entities.User, GestionProduit.Domain, Version=1.0.0.0, Culture=neutral, PublicKeyToken=null]]",
        "MediaTypes": [
          "text/plain",
          "application/json",
          "text/json"
        ],
        "StatusCode": 200
      }
    ]
  },
  {
    "ContainingType": "GestionProduit.API.Controllers.UserController",
    "Method": "DeleteUser",
    "RelativePath": "api/User/{id}",
    "HttpMethod": "DELETE",
    "IsController": true,
    "Order": 0,
    "Parameters": [
      {
        "Name": "id",
        "Type": "System.Guid",
        "IsRequired": true
      }
    ],
    "ReturnTypes": []
  },
  {
    "ContainingType": "GestionProduit.API.Controllers.UserController",
    "Method": "UpdateUserRole",
    "RelativePath": "api/User/{id}/role",
    "HttpMethod": "PUT",
    "IsController": true,
    "Order": 0,
    "Parameters": [
      {
        "Name": "id",
        "Type": "System.Guid",
        "IsRequired": true
      },
      {
        "Name": "newRole",
        "Type": "System.String",
        "IsRequired": true
      }
    ],
    "ReturnTypes": []
  }
]